{
  "image_idx": 1556,
  "approved": true,
  "vlm_response": "yes, the object classes and segmentation masks are accurate. the computer has correctly identified the stop sign in the image. the segmentation mask for the stop sign is well-defined, clearly outlining the red octagonal shape with the word \"stop\" in white letters. there are no other objects misclassified or poorly segmented in the image.",
  "prediction": {
    "classes": [
      "stop sign"
    ],
    "class_ids": [
      3
    ],
    "scores": [
      0.99090576171875
    ],
    "boxes": [
      [
        523.9848022460938,
        171.3788299560547,
        584.082763671875,
        227.4798583984375
      ]
    ],
    "masks_contours": [
      [
        [
          540,
          171,
          539,
          172,
          538,
          172,
          529,
          181,
          528,
          181,
          526,
          183,
          526,
          184,
          525,
          185,
          525,
          186,
          524,
          187,
          524,
          208,
          525,
          209,
          525,
          210,
          526,
          211,
          526,
          212,
          532,
          218,
          533,
          218,
          537,
          222,
          537,
          223,
          539,
          225,
          540,
          225,
          541,
          226,
          543,
          226,
          544,
          227,
          564,
          227,
          565,
          226,
          566,
          226,
          571,
          221,
          572,
          221,
          573,
          220,
          573,
          219,
          577,
          215,
          577,
          214,
          578,
          213,
          579,
          213,
          581,
          211,
          581,
          210,
          582,
          209,
          582,
          184,
          577,
          179,
          576,
          179,
          575,
          178,
          574,
          178,
          572,
          176,
          571,
          176,
          567,
          172,
          566,
          172,
          565,
          171
        ]
      ]
    ]
  },
  "ground_truth": {
    "classes": [
      "stop sign"
    ],
    "class_ids": [
      13
    ],
    "boxes": [
      [
        523.1500244140625,
        171.50999450683594,
        586.7899780273438,
        228.6699981689453
      ]
    ],
    "masks_contours": [
      [
        [
          541,
          172,
          539,
          174,
          538,
          174,
          535,
          177,
          534,
          177,
          531,
          180,
          530,
          180,
          528,
          182,
          527,
          182,
          524,
          185,
          523,
          185,
          523,
          206,
          545,
          228,
          546,
          227,
          555,
          227,
          556,
          226,
          564,
          226,
          565,
          225,
          566,
          225,
          569,
          222,
          570,
          222,
          572,
          220,
          573,
          220,
          575,
          218,
          576,
          218,
          579,
          215,
          580,
          215,
          582,
          213,
          583,
          213,
          583,
          212,
          584,
          211,
          584,
          202,
          585,
          201,
          585,
          193,
          586,
          192,
          586,
          189,
          578,
          181,
          577,
          181,
          568,
          172
        ]
      ]
    ]
  }
}