{
  "image_idx": 10,
  "approved": true,
  "vlm_response": "after carefully examining the image, i have visually identified two objects: a green mask and a red mask, both of which are of birds. the green mask is on the left and the red mask is on the right. both objects are correctly detected and fit the description of birds. the masks are not overly tight, and there is no background spill-over. there are no errors in the detections.\n\n*yes*\n\n*no \u2013 the objects are correctly detected and the masks are good.",
  "prediction": {
    "classes": [
      "bird",
      "bird"
    ],
    "class_ids": [
      2,
      2
    ],
    "scores": [
      0.996582567691803,
      0.9953937530517578
    ],
    "boxes": [
      [
        449.6451110839844,
        207.4728546142578,
        503.3462219238281,
        266.6637878417969
      ],
      [
        190.53102111816406,
        188.55931091308594,
        237.29664611816406,
        238.26585388183594
      ]
    ],
    "masks_contours": [
      [
        [
          481,
          210,
          480,
          211,
          478,
          211,
          476,
          213,
          475,
          213,
          472,
          216,
          472,
          217,
          467,
          222,
          466,
          222,
          465,
          223,
          465,
          224,
          464,
          225,
          464,
          227,
          463,
          228,
          463,
          229,
          462,
          230,
          462,
          239,
          461,
          240,
          461,
          241,
          460,
          242,
          460,
          243,
          458,
          245,
          458,
          246,
          455,
          249,
          455,
          250,
          453,
          252,
          453,
          255,
          452,
          256,
          452,
          261,
          453,
          262,
          453,
          263,
          455,
          265,
          471,
          265,
          472,
          264,
          482,
          264,
          483,
          265,
          484,
          264,
          497,
          264,
          498,
          263,
          499,
          263,
          500,
          264,
          501,
          264,
          501,
          263,
          502,
          262,
          502,
          261,
          503,
          260,
          503,
          257,
          502,
          256,
          502,
          253,
          501,
          252,
          501,
          250,
          500,
          250,
          499,
          249,
          499,
          248,
          497,
          246,
          497,
          245,
          495,
          243,
          495,
          242,
          493,
          240,
          493,
          239,
          492,
          238,
          492,
          233,
          493,
          232,
          493,
          228,
          494,
          227,
          494,
          221,
          493,
          220,
          493,
          216,
          492,
          215,
          492,
          214,
          491,
          213,
          491,
          212,
          490,
          211,
          488,
          211,
          487,
          210
        ]
      ],
      [
        [
          211,
          189,
          210,
          190,
          209,
          190,
          208,
          191,
          208,
          192,
          206,
          194,
          206,
          197,
          205,
          198,
          205,
          200,
          204,
          201,
          204,
          208,
          203,
          209,
          203,
          210,
          202,
          211,
          202,
          212,
          197,
          217,
          197,
          218,
          196,
          219,
          196,
          220,
          195,
          221,
          195,
          222,
          193,
          224,
          193,
          225,
          192,
          226,
          192,
          228,
          191,
          229,
          191,
          230,
          192,
          231,
          192,
          234,
          193,
          235,
          193,
          236,
          194,
          237,
          203,
          237,
          204,
          236,
          207,
          236,
          208,
          235,
          230,
          235,
          231,
          236,
          233,
          234,
          234,
          234,
          235,
          233,
          235,
          232,
          236,
          231,
          236,
          223,
          235,
          222,
          235,
          221,
          224,
          210,
          223,
          210,
          221,
          208,
          222,
          207,
          222,
          206,
          223,
          205,
          226,
          205,
          227,
          204,
          228,
          204,
          228,
          200,
          225,
          197,
          225,
          196,
          221,
          192,
          220,
          192,
          218,
          190,
          216,
          190,
          215,
          189
        ]
      ]
    ]
  },
  "ground_truth": {
    "classes": [
      "bird"
    ],
    "class_ids": [
      16,
      16
    ],
    "boxes": [
      [
        452.9599914550781,
        209.85000610351562,
        505.3800048828125,
        266.1700134277344
      ],
      [
        191.3300018310547,
        189.67999267578125,
        239.1300048828125,
        235.64999389648438
      ]
    ],
    "masks_contours": [
      [
        [
          480,
          210,
          479,
          211,
          477,
          211,
          475,
          213,
          475,
          214,
          471,
          218,
          471,
          219,
          470,
          220,
          469,
          220,
          466,
          223,
          465,
          223,
          467,
          223,
          468,
          224,
          473,
          224,
          474,
          223,
          480,
          223,
          481,
          224,
          483,
          224,
          484,
          225,
          484,
          230,
          483,
          231,
          480,
          231,
          479,
          230,
          471,
          230,
          470,
          229,
          463,
          229,
          463,
          231,
          462,
          232,
          462,
          236,
          463,
          237,
          463,
          240,
          461,
          242,
          461,
          243,
          458,
          246,
          458,
          247,
          455,
          250,
          455,
          251,
          453,
          253,
          453,
          260,
          454,
          260,
          455,
          261,
          456,
          261,
          458,
          263,
          462,
          263,
          463,
          264,
          469,
          264,
          470,
          265,
          490,
          265,
          491,
          264,
          495,
          264,
          496,
          263,
          499,
          263,
          500,
          262,
          501,
          262,
          502,
          261,
          503,
          261,
          504,
          260,
          504,
          259,
          500,
          255,
          500,
          253,
          499,
          252,
          499,
          251,
          498,
          250,
          498,
          248,
          497,
          247,
          497,
          246,
          495,
          244,
          495,
          243,
          494,
          242,
          494,
          241,
          492,
          239,
          492,
          238,
          491,
          237,
          491,
          236,
          490,
          235,
          491,
          234,
          491,
          227,
          492,
          226,
          492,
          216,
          491,
          215,
          491,
          213,
          490,
          212,
          489,
          212,
          488,
          211,
          487,
          211,
          486,
          210
        ]
      ],
      [
        [
          210,
          190,
          207,
          193,
          207,
          194,
          206,
          195,
          206,
          197,
          205,
          198,
          205,
          203,
          206,
          204,
          206,
          209,
          204,
          211,
          203,
          211,
          200,
          214,
          200,
          215,
          199,
          216,
          199,
          217,
          197,
          219,
          197,
          220,
          196,
          221,
          196,
          222,
          194,
          224,
          194,
          225,
          192,
          227,
          192,
          228,
          191,
          229,
          192,
          230,
          192,
          233,
          195,
          233,
          196,
          234,
          210,
          234,
          211,
          235,
          219,
          235,
          220,
          234,
          234,
          234,
          236,
          232,
          237,
          232,
          238,
          231,
          238,
          226,
          237,
          225,
          237,
          224,
          236,
          223,
          236,
          222,
          235,
          221,
          235,
          220,
          234,
          220,
          231,
          217,
          231,
          216,
          225,
          210,
          224,
          210,
          223,
          209,
          222,
          209,
          221,
          208,
          219,
          208,
          218,
          207,
          217,
          207,
          216,
          208,
          215,
          207,
          215,
          204,
          216,
          203,
          225,
          203,
          226,
          202,
          227,
          202,
          228,
          203,
          231,
          203,
          228,
          200,
          228,
          199,
          227,
          198,
          226,
          198,
          225,
          197,
          224,
          197,
          222,
          195,
          222,
          192,
          220,
          192,
          219,
          191,
          218,
          191,
          217,
          190
        ]
      ]
    ]
  }
}