{
  "image_idx": 776,
  "approved": true,
  "vlm_response": "yes, the object classes and segmentation masks appear to be accurate. the image shows two birds, one green and one red, which are correctly identified by the computer. the segmentation masks accurately highlight the birds, distinguishing them from the background. the additional colored areas, such as the blue and yellow shapes, are likely part of the beach environment and do not affect the accuracy of the bird segmentation.",
  "prediction": {
    "classes": [
      "bird",
      "bird"
    ],
    "class_ids": [
      2,
      2
    ],
    "scores": [
      0.9955098628997803,
      0.9920985698699951
    ],
    "boxes": [
      [
        367.2200622558594,
        228.40802001953125,
        420.0445556640625,
        290.64398193359375
      ],
      [
        139.38246154785156,
        215.2410430908203,
        205.93911743164062,
        290.698486328125
      ]
    ],
    "masks_contours": [
      [
        [
          413,
          230,
          412,
          231,
          411,
          231,
          410,
          232,
          410,
          233,
          409,
          234,
          409,
          246,
          410,
          247,
          409,
          248,
          409,
          251,
          407,
          253,
          402,
          253,
          401,
          254,
          400,
          254,
          399,
          255,
          398,
          255,
          397,
          256,
          396,
          256,
          395,
          257,
          394,
          257,
          393,
          258,
          392,
          258,
          391,
          259,
          389,
          259,
          388,
          260,
          387,
          260,
          386,
          261,
          385,
          261,
          382,
          264,
          381,
          264,
          380,
          265,
          380,
          266,
          378,
          268,
          377,
          268,
          377,
          269,
          375,
          271,
          375,
          272,
          374,
          273,
          374,
          274,
          373,
          275,
          373,
          277,
          372,
          278,
          372,
          280,
          371,
          281,
          371,
          288,
          372,
          288,
          373,
          287,
          374,
          287,
          375,
          286,
          378,
          286,
          379,
          285,
          382,
          285,
          383,
          284,
          386,
          284,
          387,
          283,
          388,
          284,
          390,
          284,
          393,
          287,
          393,
          288,
          394,
          289,
          395,
          289,
          395,
          283,
          399,
          279,
          400,
          279,
          401,
          278,
          402,
          278,
          405,
          275,
          406,
          275,
          410,
          271,
          410,
          270,
          412,
          268,
          412,
          267,
          413,
          266,
          413,
          265,
          414,
          264,
          414,
          263,
          415,
          262,
          415,
          259,
          416,
          258,
          416,
          247,
          415,
          246,
          415,
          239,
          416,
          238,
          416,
          232,
          415,
          231,
          414,
          231
        ]
      ],
      [
        [
          188,
          216,
          185,
          219,
          185,
          223,
          186,
          224,
          186,
          225,
          187,
          226,
          187,
          229,
          188,
          230,
          188,
          231,
          189,
          232,
          189,
          233,
          190,
          234,
          190,
          235,
          191,
          236,
          191,
          237,
          192,
          238,
          192,
          244,
          191,
          245,
          191,
          246,
          187,
          250,
          186,
          250,
          185,
          251,
          184,
          251,
          182,
          253,
          180,
          253,
          178,
          255,
          176,
          255,
          175,
          256,
          174,
          256,
          173,
          257,
          172,
          257,
          171,
          258,
          169,
          258,
          167,
          260,
          166,
          260,
          165,
          261,
          164,
          261,
          155,
          270,
          155,
          271,
          151,
          275,
          151,
          276,
          150,
          277,
          150,
          278,
          149,
          279,
          149,
          280,
          147,
          282,
          147,
          287,
          152,
          287,
          153,
          286,
          156,
          286,
          157,
          285,
          165,
          285,
          166,
          284,
          167,
          284,
          168,
          285,
          175,
          285,
          176,
          284,
          177,
          284,
          178,
          283,
          178,
          281,
          182,
          277,
          183,
          277,
          185,
          275,
          186,
          275,
          188,
          273,
          189,
          273,
          192,
          270,
          192,
          269,
          193,
          268,
          193,
          267,
          194,
          266,
          194,
          264,
          195,
          263,
          195,
          261,
          196,
          260,
          196,
          259,
          197,
          258,
          197,
          257,
          198,
          256,
          199,
          256,
          200,
          255,
          201,
          255,
          202,
          256,
          205,
          256,
          205,
          247,
          204,
          246,
          204,
          245,
          203,
          244,
          203,
          243,
          202,
          242,
          202,
          241,
          201,
          240,
          201,
          239,
          200,
          238,
          200,
          236,
          199,
          235,
          199,
          233,
          198,
          232,
          198,
          229,
          197,
          228,
          197,
          225,
          196,
          224,
          196,
          219,
          193,
          216
        ]
      ]
    ]
  },
  "ground_truth": {
    "classes": [
      "bird"
    ],
    "class_ids": [
      16,
      16
    ],
    "boxes": [
      [
        146.1300048828125,
        213.8699951171875,
        206.6999969482422,
        290.25
      ],
      [
        368.2799987792969,
        228.85000610351562,
        417.69000244140625,
        293.9100036621094
      ]
    ],
    "masks_contours": [
      [
        [
          185,
          214,
          185,
          226,
          186,
          227,
          186,
          228,
          187,
          229,
          187,
          230,
          188,
          231,
          188,
          232,
          189,
          233,
          189,
          235,
          190,
          236,
          190,
          237,
          191,
          238,
          191,
          239,
          192,
          240,
          192,
          241,
          193,
          242,
          193,
          243,
          194,
          244,
          194,
          245,
          195,
          246,
          195,
          247,
          194,
          248,
          193,
          248,
          192,
          249,
          184,
          249,
          183,
          250,
          182,
          250,
          180,
          252,
          179,
          252,
          178,
          253,
          177,
          253,
          175,
          255,
          174,
          255,
          173,
          256,
          172,
          256,
          171,
          257,
          170,
          257,
          168,
          259,
          167,
          259,
          166,
          260,
          165,
          260,
          163,
          262,
          162,
          262,
          161,
          263,
          160,
          263,
          159,
          264,
          158,
          264,
          157,
          265,
          157,
          266,
          155,
          268,
          155,
          269,
          154,
          270,
          154,
          271,
          153,
          272,
          153,
          273,
          151,
          275,
          151,
          276,
          150,
          277,
          150,
          278,
          148,
          280,
          148,
          282,
          147,
          283,
          147,
          286,
          149,
          286,
          150,
          285,
          152,
          285,
          153,
          284,
          155,
          284,
          156,
          283,
          158,
          283,
          159,
          282,
          161,
          282,
          162,
          281,
          164,
          281,
          165,
          280,
          167,
          280,
          168,
          279,
          170,
          279,
          171,
          280,
          171,
          283,
          172,
          284,
          172,
          286,
          173,
          287,
          173,
          289,
          174,
          289,
          175,
          288,
          177,
          288,
          178,
          287,
          180,
          287,
          172,
          279,
          173,
          278,
          175,
          278,
          176,
          277,
          183,
          277,
          184,
          276,
          187,
          276,
          188,
          275,
          188,
          273,
          189,
          272,
          189,
          270,
          190,
          269,
          190,
          268,
          191,
          267,
          191,
          265,
          192,
          264,
          192,
          262,
          193,
          261,
          193,
          259,
          194,
          258,
          194,
          256,
          195,
          255,
          195,
          253,
          196,
          252,
          196,
          251,
          197,
          250,
          197,
          249,
          198,
          248,
          202,
          252,
          202,
          253,
          206,
          257,
          205,
          256,
          205,
          254,
          204,
          253,
          204,
          250,
          203,
          249,
          203,
          246,
          202,
          245,
          202,
          243,
          201,
          242,
          201,
          239,
          200,
          238,
          200,
          235,
          199,
          234,
          199,
          232,
          198,
          231,
          198,
          228,
          197,
          227,
          197,
          224,
          196,
          223,
          196,
          220,
          195,
          219,
          195,
          217,
          194,
          217,
          193,
          216,
          190,
          216,
          189,
          215,
          187,
          215,
          186,
          214
        ]
      ],
      [
        [
          411,
          229,
          411,
          230,
          410,
          231,
          410,
          232,
          409,
          233,
          409,
          246,
          410,
          247,
          410,
          253,
          409,
          254,
          407,
          254,
          406,
          253,
          405,
          253,
          404,
          252,
          403,
          252,
          402,
          253,
          401,
          253,
          400,
          254,
          399,
          254,
          398,
          255,
          397,
          255,
          396,
          256,
          395,
          256,
          394,
          257,
          392,
          257,
          391,
          258,
          390,
          258,
          389,
          259,
          388,
          259,
          387,
          260,
          386,
          260,
          385,
          261,
          384,
          261,
          383,
          262,
          382,
          262,
          381,
          263,
          381,
          264,
          377,
          268,
          377,
          269,
          375,
          271,
          375,
          272,
          374,
          273,
          374,
          274,
          373,
          275,
          373,
          277,
          372,
          278,
          372,
          279,
          371,
          280,
          371,
          281,
          370,
          282,
          370,
          284,
          369,
          285,
          369,
          286,
          368,
          287,
          368,
          289,
          369,
          289,
          371,
          287,
          372,
          287,
          373,
          286,
          375,
          286,
          376,
          285,
          380,
          285,
          381,
          284,
          389,
          284,
          390,
          285,
          390,
          286,
          391,
          287,
          391,
          288,
          392,
          289,
          392,
          290,
          393,
          291,
          393,
          292,
          392,
          293,
          393,
          293,
          394,
          292,
          395,
          292,
          397,
          290,
          397,
          289,
          396,
          288,
          396,
          287,
          395,
          286,
          395,
          283,
          394,
          282,
          395,
          281,
          396,
          281,
          397,
          280,
          398,
          280,
          399,
          279,
          400,
          279,
          402,
          277,
          403,
          277,
          410,
          270,
          410,
          269,
          413,
          266,
          413,
          265,
          414,
          264,
          414,
          263,
          415,
          262,
          415,
          258,
          416,
          257,
          416,
          253,
          417,
          252,
          416,
          251,
          416,
          247,
          415,
          246,
          415,
          242,
          414,
          241,
          415,
          240,
          415,
          239,
          416,
          238,
          416,
          231,
          414,
          229
        ]
      ]
    ]
  }
}