{
  "image_idx": 1268,
  "approved": false,
  "vlm_response": "the image shows a street scene with various objects, including traffic lights, cars, and a signboard. the computer's detection of \"no objects\" is inaccurate. the segmentation masks should identify the traffic lights, cars, and signboard, among other objects. the masks are not accurately identifying the objects in the image. therefore, the answer is:\n\nno",
  "prediction": {
    "classes": [],
    "class_ids": [],
    "scores": [],
    "boxes": [],
    "masks_contours": []
  },
  "ground_truth": {
    "classes": [
      "stop sign"
    ],
    "class_ids": [
      13
    ],
    "boxes": [
      [
        446.510009765625,
        43.959999084472656,
        492.57000732421875,
        92.06999969482422
      ]
    ],
    "masks_contours": [
      [
        [
          464,
          44,
          459,
          49,
          458,
          49,
          451,
          56,
          451,
          58,
          450,
          59,
          450,
          62,
          449,
          63,
          449,
          66,
          448,
          67,
          448,
          70,
          447,
          71,
          447,
          75,
          448,
          76,
          448,
          77,
          450,
          79,
          450,
          80,
          451,
          81,
          451,
          82,
          453,
          84,
          453,
          85,
          458,
          90,
          458,
          91,
          473,
          91,
          475,
          89,
          476,
          89,
          481,
          84,
          482,
          84,
          482,
          83,
          483,
          82,
          483,
          81,
          485,
          79,
          485,
          78,
          486,
          77,
          486,
          76,
          488,
          74,
          488,
          73,
          489,
          72,
          489,
          71,
          491,
          69,
          491,
          68,
          492,
          67,
          491,
          66,
          491,
          62,
          490,
          61,
          490,
          56,
          489,
          55,
          489,
          52,
          488,
          51,
          487,
          51,
          485,
          49,
          484,
          49,
          483,
          48,
          482,
          48,
          480,
          46,
          479,
          46,
          477,
          44
        ]
      ]
    ]
  }
}