{
  "image_idx": 1322,
  "approved": false,
  "vlm_response": "the image shows a zebra with a red outline, indicating the segmentation mask. the computer's detection of \"no objects\" is incorrect, as the zebra is clearly the main object in the image. the segmentation mask is not accurately identifying the zebra, as it is not labeled as an object. therefore, the answer is:\n\nno, the object classes and segmentation masks are not accurate.",
  "prediction": {
    "classes": [],
    "class_ids": [],
    "scores": [],
    "boxes": [],
    "masks_contours": []
  },
  "ground_truth": {
    "classes": [
      "zebra"
    ],
    "class_ids": [
      24
    ],
    "boxes": [
      [
        130.49000549316406,
        125.26000213623047,
        466.8699951171875,
        414.1600036621094
      ]
    ],
    "masks_contours": [
      [
        [
          172,
          125,
          171,
          126,
          170,
          126,
          169,
          127,
          168,
          127,
          167,
          128,
          165,
          128,
          164,
          129,
          163,
          129,
          155,
          137,
          154,
          136,
          153,
          136,
          147,
          130,
          145,
          130,
          144,
          131,
          140,
          131,
          139,
          132,
          141,
          134,
          141,
          135,
          142,
          136,
          142,
          137,
          144,
          139,
          144,
          140,
          145,
          141,
          145,
          142,
          146,
          143,
          146,
          144,
          148,
          146,
          148,
          147,
          149,
          148,
          149,
          149,
          150,
          150,
          150,
          151,
          152,
          153,
          152,
          155,
          150,
          157,
          150,
          158,
          148,
          160,
          148,
          161,
          144,
          165,
          144,
          166,
          141,
          169,
          141,
          173,
          140,
          174,
          140,
          178,
          139,
          179,
          139,
          184,
          138,
          185,
          138,
          189,
          137,
          190,
          137,
          193,
          136,
          194,
          136,
          196,
          135,
          197,
          135,
          199,
          134,
          200,
          134,
          202,
          133,
          203,
          133,
          206,
          132,
          207,
          132,
          209,
          131,
          210,
          131,
          212,
          130,
          213,
          131,
          214,
          131,
          218,
          132,
          219,
          132,
          221,
          133,
          222,
          133,
          224,
          134,
          225,
          134,
          227,
          142,
          227,
          143,
          228,
          151,
          228,
          151,
          226,
          152,
          225,
          152,
          224,
          159,
          217,
          160,
          217,
          161,
          216,
          163,
          216,
          164,
          215,
          165,
          215,
          166,
          214,
          167,
          214,
          168,
          213,
          169,
          213,
          170,
          212,
          172,
          212,
          173,
          211,
          174,
          211,
          175,
          210,
          176,
          211,
          176,
          214,
          177,
          215,
          177,
          218,
          178,
          219,
          178,
          221,
          179,
          222,
          179,
          225,
          180,
          226,
          180,
          227,
          181,
          228,
          181,
          229,
          183,
          231,
          183,
          232,
          186,
          235,
          186,
          236,
          189,
          239,
          189,
          240,
          191,
          242,
          191,
          243,
          194,
          246,
          194,
          247,
          196,
          249,
          196,
          251,
          197,
          252,
          197,
          253,
          198,
          254,
          198,
          255,
          199,
          256,
          199,
          258,
          200,
          259,
          200,
          260,
          201,
          261,
          201,
          262,
          202,
          263,
          202,
          264,
          203,
          265,
          203,
          267,
          204,
          268,
          204,
          269,
          205,
          270,
          205,
          271,
          206,
          272,
          206,
          274,
          208,
          276,
          208,
          277,
          214,
          283,
          214,
          284,
          221,
          291,
          222,
          291,
          225,
          294,
          226,
          294,
          227,
          295,
          227,
          296,
          232,
          301,
          232,
          306,
          233,
          307,
          233,
          315,
          234,
          316,
          234,
          322,
          233,
          323,
          233,
          336,
          232,
          337,
          232,
          338,
          233,
          339,
          233,
          341,
          234,
          342,
          234,
          343,
          235,
          344,
          235,
          346,
          236,
          347,
          236,
          349,
          237,
          350,
          237,
          352,
          236,
          353,
          236,
          375,
          235,
          376,
          235,
          377,
          234,
          378,
          234,
          379,
          233,
          380,
          233,
          381,
          231,
          383,
          231,
          384,
          230,
          385,
          230,
          386,
          226,
          390,
          225,
          390,
          223,
          392,
          223,
          393,
          222,
          394,
          222,
          395,
          221,
          396,
          221,
          397,
          219,
          399,
          219,
          400,
          218,
          401,
          218,
          402,
          217,
          403,
          217,
          404,
          216,
          405,
          216,
          406,
          217,
          405,
          229,
          405,
          230,
          404,
          240,
          404,
          242,
          402,
          242,
          400,
          241,
          399,
          241,
          396,
          240,
          395,
          240,
          392,
          239,
          391,
          239,
          389,
          241,
          387,
          241,
          386,
          243,
          384,
          243,
          382,
          244,
          381,
          244,
          378,
          245,
          377,
          245,
          370,
          246,
          369,
          246,
          357,
          247,
          356,
          247,
          346,
          248,
          345,
          248,
          342,
          249,
          341,
          251,
          343,
          251,
          344,
          254,
          347,
          254,
          348,
          257,
          351,
          257,
          352,
          258,
          353,
          258,
          354,
          259,
          355,
          259,
          365,
          260,
          366,
          260,
          377,
          261,
          378,
          261,
          381,
          260,
          382,
          260,
          386,
          259,
          387,
          259,
          389,
          258,
          390,
          258,
          391,
          255,
          394,
          255,
          395,
          252,
          398,
          252,
          399,
          251,
          400,
          251,
          402,
          250,
          403,
          250,
          405,
          249,
          406,
          249,
          408,
          248,
          409,
          248,
          412,
          249,
          412,
          250,
          411,
          260,
          411,
          261,
          410,
          262,
          410,
          263,
          409,
          265,
          409,
          266,
          408,
          268,
          408,
          269,
          407,
          271,
          407,
          272,
          406,
          274,
          406,
          273,
          405,
          273,
          402,
          272,
          401,
          272,
          398,
          271,
          397,
          271,
          396,
          273,
          394,
          273,
          393,
          275,
          391,
          275,
          390,
          277,
          388,
          277,
          387,
          279,
          385,
          279,
          382,
          278,
          381,
          278,
          379,
          277,
          378,
          277,
          376,
          276,
          375,
          276,
          373,
          275,
          372,
          275,
          369,
          274,
          368,
          274,
          366,
          273,
          365,
          273,
          363,
          272,
          362,
          272,
          360,
          271,
          359,
          271,
          358,
          270,
          357,
          270,
          356,
          269,
          355,
          269,
          354,
          268,
          353,
          268,
          352,
          267,
          351,
          267,
          345,
          266,
          344,
          266,
          326,
          265,
          325,
          265,
          314,
          264,
          313,
          264,
          310,
          263,
          309,
          263,
          306,
          262,
          305,
          262,
          302,
          261,
          301,
          261,
          298,
          260,
          297,
          260,
          295,
          261,
          294,
          262,
          295,
          263,
          295,
          264,
          296,
          267,
          296,
          268,
          297,
          271,
          297,
          272,
          298,
          278,
          298,
          279,
          299,
          285,
          299,
          286,
          300,
          291,
          300,
          292,
          301,
          298,
          301,
          299,
          302,
          305,
          302,
          306,
          303,
          312,
          303,
          313,
          304,
          319,
          304,
          320,
          303,
          323,
          303,
          324,
          302,
          328,
          302,
          329,
          301,
          332,
          301,
          333,
          300,
          336,
          300,
          337,
          299,
          340,
          299,
          341,
          298,
          344,
          298,
          345,
          297,
          348,
          297,
          349,
          296,
          352,
          296,
          353,
          295,
          356,
          295,
          357,
          294,
          359,
          294,
          360,
          293,
          361,
          293,
          363,
          291,
          363,
          290,
          366,
          287,
          366,
          286,
          369,
          283,
          370,
          283,
          372,
          281,
          373,
          281,
          375,
          279,
          376,
          279,
          379,
          282,
          379,
          283,
          380,
          284,
          380,
          285,
          381,
          286,
          381,
          287,
          382,
          288,
          382,
          289,
          383,
          290,
          383,
          291,
          384,
          292,
          384,
          293,
          385,
          294,
          385,
          295,
          386,
          296,
          386,
          297,
          387,
          298,
          387,
          300,
          388,
          301,
          388,
          302,
          389,
          303,
          389,
          304,
          390,
          305,
          390,
          307,
          391,
          308,
          391,
          309,
          392,
          310,
          392,
          311,
          393,
          312,
          393,
          314,
          394,
          315,
          394,
          316,
          395,
          317,
          395,
          318,
          396,
          319,
          396,
          320,
          397,
          321,
          397,
          323,
          398,
          324,
          398,
          325,
          399,
          326,
          399,
          327,
          400,
          328,
          400,
          329,
          401,
          330,
          401,
          333,
          402,
          334,
          402,
          336,
          403,
          337,
          403,
          339,
          404,
          340,
          404,
          343,
          405,
          344,
          405,
          346,
          406,
          347,
          406,
          352,
          405,
          353,
          405,
          358,
          404,
          359,
          404,
          364,
          403,
          365,
          403,
          370,
          402,
          371,
          402,
          376,
          401,
          377,
          401,
          381,
          400,
          382,
          400,
          385,
          399,
          386,
          399,
          389,
          398,
          390,
          398,
          393,
          396,
          395,
          393,
          395,
          392,
          396,
          389,
          396,
          389,
          398,
          388,
          399,
          388,
          401,
          387,
          402,
          387,
          403,
          386,
          404,
          386,
          406,
          385,
          407,
          385,
          408,
          384,
          409,
          384,
          411,
          383,
          412,
          383,
          413,
          386,
          413,
          387,
          412,
          392,
          412,
          393,
          411,
          398,
          411,
          399,
          410,
          404,
          410,
          405,
          409,
          407,
          409,
          407,
          406,
          408,
          405,
          408,
          396,
          409,
          395,
          417,
          395,
          418,
          396,
          419,
          396,
          419,
          395,
          417,
          393,
          417,
          391,
          416,
          390,
          416,
          374,
          417,
          373,
          417,
          369,
          418,
          368,
          418,
          365,
          419,
          364,
          419,
          360,
          420,
          359,
          420,
          356,
          421,
          355,
          421,
          351,
          422,
          350,
          422,
          347,
          423,
          346,
          423,
          344,
          424,
          343,
          424,
          341,
          425,
          340,
          425,
          338,
          426,
          337,
          426,
          335,
          427,
          334,
          429,
          336,
          429,
          337,
          430,
          338,
          430,
          339,
          431,
          340,
          431,
          341,
          432,
          342,
          432,
          343,
          433,
          344,
          433,
          345,
          434,
          346,
          434,
          347,
          435,
          348,
          435,
          362,
          436,
          363,
          436,
          381,
          437,
          382,
          437,
          383,
          436,
          384,
          436,
          386,
          435,
          387,
          435,
          389,
          434,
          390,
          434,
          392,
          433,
          393,
          433,
          395,
          432,
          396,
          432,
          398,
          431,
          399,
          431,
          402,
          430,
          403,
          430,
          405,
          429,
          406,
          429,
          409,
          428,
          410,
          438,
          410,
          439,
          409,
          442,
          409,
          443,
          408,
          446,
          408,
          447,
          407,
          448,
          407,
          451,
          404,
          450,
          403,
          450,
          401,
          449,
          400,
          449,
          398,
          448,
          397,
          448,
          395,
          450,
          393,
          450,
          392,
          452,
          390,
          454,
          390,
          455,
          389,
          456,
          389,
          456,
          386,
          455,
          385,
          455,
          383,
          454,
          382,
          454,
          379,
          453,
          378,
          453,
          375,
          452,
          374,
          452,
          371,
          451,
          370,
          451,
          367,
          450,
          366,
          450,
          363,
          449,
          362,
          449,
          359,
          450,
          358,
          451,
          359,
          451,
          360,
          452,
          361,
          452,
          362,
          453,
          363,
          453,
          364,
          454,
          365,
          454,
          366,
          455,
          367,
          455,
          368,
          456,
          369,
          456,
          370,
          457,
          371,
          457,
          372,
          458,
          373,
          458,
          374,
          459,
          375,
          459,
          376,
          460,
          377,
          460,
          378,
          461,
          379,
          461,
          380,
          462,
          381,
          462,
          382,
          463,
          383,
          463,
          384,
          463,
          367,
          464,
          366,
          464,
          361,
          465,
          360,
          465,
          354,
          466,
          353,
          466,
          350,
          465,
          349,
          465,
          341,
          464,
          340,
          464,
          333,
          463,
          332,
          463,
          325,
          462,
          324,
          462,
          317,
          461,
          316,
          461,
          309,
          460,
          308,
          460,
          302,
          459,
          301,
          459,
          294,
          458,
          293,
          458,
          287,
          457,
          286,
          457,
          280,
          456,
          279,
          456,
          274,
          455,
          273,
          455,
          266,
          454,
          265,
          454,
          257,
          453,
          256,
          453,
          247,
          452,
          246,
          452,
          239,
          451,
          238,
          451,
          236,
          450,
          235,
          450,
          233,
          449,
          232,
          449,
          230,
          448,
          229,
          448,
          227,
          447,
          226,
          447,
          224,
          446,
          223,
          446,
          221,
          445,
          220,
          445,
          218,
          444,
          217,
          444,
          216,
          443,
          215,
          443,
          213,
          442,
          212,
          442,
          210,
          441,
          209,
          441,
          207,
          440,
          206,
          440,
          204,
          424,
          188,
          422,
          188,
          421,
          187,
          415,
          187,
          414,
          186,
          407,
          186,
          406,
          185,
          400,
          185,
          399,
          184,
          392,
          184,
          391,
          183,
          382,
          183,
          381,
          184,
          379,
          184,
          378,
          185,
          375,
          185,
          374,
          186,
          371,
          186,
          370,
          187,
          368,
          187,
          367,
          188,
          364,
          188,
          363,
          189,
          361,
          189,
          360,
          190,
          357,
          190,
          356,
          191,
          353,
          191,
          352,
          192,
          350,
          192,
          349,
          193,
          346,
          193,
          345,
          194,
          340,
          194,
          339,
          195,
          331,
          195,
          330,
          196,
          322,
          196,
          321,
          197,
          313,
          197,
          312,
          198,
          303,
          198,
          302,
          197,
          298,
          197,
          297,
          196,
          293,
          196,
          292,
          195,
          289,
          195,
          288,
          194,
          284,
          194,
          283,
          193,
          279,
          193,
          278,
          192,
          273,
          192,
          272,
          191,
          266,
          191,
          265,
          190,
          259,
          190,
          258,
          189,
          250,
          189,
          249,
          188,
          247,
          188,
          246,
          187,
          246,
          185,
          245,
          184,
          245,
          179,
          244,
          178,
          244,
          173,
          243,
          172,
          243,
          170,
          242,
          170,
          240,
          168,
          239,
          168,
          237,
          166,
          236,
          166,
          234,
          164,
          233,
          164,
          231,
          162,
          230,
          162,
          228,
          160,
          227,
          160,
          225,
          158,
          224,
          158,
          222,
          156,
          221,
          156,
          219,
          154,
          218,
          154,
          216,
          152,
          215,
          152,
          213,
          150,
          212,
          150,
          210,
          148,
          209,
          148,
          207,
          146,
          206,
          146,
          204,
          144,
          203,
          144,
          201,
          142,
          200,
          142,
          198,
          140,
          197,
          140,
          195,
          138,
          194,
          138,
          192,
          136,
          191,
          136,
          190,
          135,
          189,
          135,
          187,
          133,
          186,
          133,
          185,
          132,
          184,
          132,
          182,
          130,
          181,
          130,
          180,
          129,
          179,
          129,
          178,
          128,
          177,
          128,
          175,
          126,
          174,
          126,
          173,
          125
        ]
      ]
    ]
  }
}