{
  "image_idx": 2057,
  "approved": false,
  "vlm_response": "the computer's detection of objects in the image is not accurate. the segmentation masks are present but do not correctly identify the objects. the masks are applied to areas that do not correspond to actual objects in the image. for example, the masks are applied to the background and other non-object areas, and some objects are not fully segmented. additionally, the masks are not clearly defined, making it difficult to discern the boundaries of the objects. therefore, the answer is \"no\" followed by an explanation of the misclassifications and poor segmentation.",
  "prediction": {
    "classes": [],
    "class_ids": [],
    "scores": [],
    "boxes": [],
    "masks_contours": []
  },
  "ground_truth": {
    "classes": [
      "book"
    ],
    "class_ids": [
      84
    ],
    "boxes": [
      [
        91.12999725341797,
        366.55999755859375,
        476.79998779296875,
        583.1500244140625
      ]
    ],
    "masks_contours": [
      [
        [
          178,
          367,
          177,
          368,
          176,
          368,
          175,
          369,
          174,
          369,
          173,
          370,
          171,
          370,
          170,
          371,
          169,
          371,
          168,
          372,
          167,
          372,
          166,
          373,
          164,
          373,
          163,
          374,
          162,
          374,
          161,
          375,
          159,
          375,
          158,
          376,
          157,
          376,
          156,
          377,
          155,
          377,
          154,
          378,
          152,
          378,
          151,
          379,
          150,
          379,
          149,
          380,
          148,
          380,
          147,
          381,
          145,
          381,
          144,
          382,
          143,
          382,
          142,
          383,
          140,
          383,
          139,
          384,
          138,
          384,
          137,
          385,
          136,
          385,
          135,
          386,
          133,
          386,
          132,
          387,
          131,
          387,
          130,
          388,
          129,
          388,
          128,
          389,
          126,
          389,
          125,
          390,
          124,
          390,
          123,
          391,
          122,
          391,
          121,
          392,
          119,
          392,
          117,
          394,
          117,
          399,
          116,
          400,
          116,
          406,
          115,
          407,
          115,
          413,
          114,
          414,
          114,
          419,
          113,
          420,
          113,
          426,
          112,
          427,
          112,
          433,
          111,
          434,
          111,
          439,
          110,
          440,
          110,
          446,
          109,
          447,
          109,
          453,
          108,
          454,
          108,
          459,
          107,
          460,
          107,
          466,
          106,
          467,
          106,
          473,
          105,
          474,
          105,
          479,
          104,
          480,
          104,
          486,
          103,
          487,
          103,
          493,
          102,
          494,
          102,
          499,
          101,
          500,
          101,
          506,
          100,
          507,
          100,
          513,
          99,
          514,
          99,
          519,
          98,
          520,
          98,
          526,
          97,
          527,
          97,
          533,
          96,
          534,
          96,
          539,
          95,
          540,
          95,
          546,
          94,
          547,
          94,
          553,
          93,
          554,
          93,
          559,
          92,
          560,
          92,
          566,
          91,
          567,
          91,
          568,
          101,
          568,
          102,
          569,
          136,
          569,
          137,
          570,
          171,
          570,
          172,
          571,
          207,
          571,
          208,
          572,
          241,
          572,
          242,
          573,
          265,
          573,
          266,
          574,
          289,
          574,
          290,
          575,
          313,
          575,
          314,
          576,
          338,
          576,
          339,
          577,
          362,
          577,
          363,
          578,
          386,
          578,
          387,
          579,
          410,
          579,
          411,
          580,
          435,
          580,
          436,
          581,
          459,
          581,
          460,
          582,
          476,
          582,
          475,
          581,
          475,
          579,
          474,
          578,
          474,
          577,
          473,
          576,
          473,
          574,
          472,
          573,
          472,
          571,
          471,
          570,
          471,
          568,
          470,
          567,
          470,
          565,
          469,
          564,
          469,
          563,
          468,
          562,
          468,
          560,
          467,
          559,
          467,
          557,
          466,
          556,
          466,
          554,
          465,
          553,
          465,
          551,
          464,
          550,
          464,
          549,
          463,
          548,
          463,
          546,
          462,
          545,
          462,
          543,
          461,
          542,
          461,
          540,
          460,
          539,
          460,
          537,
          459,
          536,
          459,
          534,
          458,
          533,
          458,
          532,
          457,
          531,
          457,
          529,
          456,
          528,
          456,
          526,
          455,
          525,
          455,
          523,
          454,
          522,
          454,
          520,
          453,
          519,
          453,
          518,
          452,
          517,
          452,
          515,
          451,
          514,
          451,
          512,
          450,
          511,
          450,
          509,
          449,
          508,
          449,
          506,
          448,
          505,
          448,
          503,
          447,
          502,
          447,
          501,
          446,
          500,
          446,
          498,
          445,
          497,
          445,
          495,
          444,
          494,
          444,
          492,
          443,
          491,
          443,
          489,
          442,
          488,
          442,
          487,
          441,
          486,
          441,
          484,
          440,
          483,
          440,
          481,
          439,
          480,
          439,
          478,
          438,
          477,
          438,
          475,
          437,
          474,
          437,
          473,
          436,
          472,
          436,
          470,
          435,
          469,
          435,
          467,
          434,
          466,
          434,
          464,
          433,
          463,
          433,
          461,
          432,
          460,
          432,
          458,
          431,
          457,
          431,
          456,
          430,
          455,
          430,
          453,
          429,
          452,
          429,
          450,
          428,
          449,
          428,
          447,
          427,
          446,
          427,
          444,
          426,
          443,
          426,
          442,
          420,
          442,
          419,
          441,
          407,
          441,
          406,
          440,
          394,
          440,
          393,
          439,
          390,
          439,
          385,
          444,
          384,
          444,
          383,
          445,
          382,
          445,
          381,
          446,
          380,
          446,
          379,
          447,
          378,
          447,
          377,
          448,
          376,
          448,
          374,
          450,
          373,
          450,
          372,
          451,
          371,
          451,
          370,
          452,
          369,
          452,
          368,
          453,
          367,
          453,
          366,
          454,
          365,
          454,
          364,
          455,
          363,
          455,
          362,
          456,
          361,
          456,
          359,
          458,
          358,
          458,
          357,
          459,
          356,
          459,
          355,
          460,
          354,
          460,
          353,
          461,
          352,
          461,
          351,
          462,
          350,
          462,
          349,
          463,
          348,
          463,
          347,
          464,
          345,
          464,
          344,
          463,
          343,
          463,
          341,
          461,
          340,
          461,
          339,
          460,
          338,
          460,
          337,
          459,
          336,
          459,
          335,
          458,
          334,
          458,
          333,
          457,
          332,
          457,
          331,
          456,
          330,
          456,
          329,
          455,
          327,
          455,
          326,
          454,
          323,
          454,
          322,
          453,
          320,
          453,
          319,
          452,
          317,
          452,
          316,
          451,
          313,
          451,
          312,
          450,
          310,
          450,
          309,
          449,
          307,
          449,
          306,
          448,
          303,
          448,
          302,
          447,
          300,
          447,
          299,
          446,
          297,
          446,
          296,
          445,
          293,
          445,
          292,
          444,
          290,
          444,
          289,
          443,
          286,
          443,
          285,
          442,
          284,
          442,
          277,
          435,
          277,
          434,
          270,
          427,
          270,
          426,
          264,
          420,
          264,
          419,
          257,
          412,
          257,
          411,
          250,
          404,
          250,
          403,
          243,
          396,
          243,
          395,
          237,
          389,
          237,
          388,
          230,
          381,
          230,
          380,
          223,
          373,
          223,
          372,
          219,
          368,
          206,
          368,
          205,
          367
        ]
      ]
    ]
  }
}